{
  "name": "micro_nod",
  "fps": 12,
  "frames": [
    {
      "duration": 70,
      "pixels": [
        {"x": 118, "y": 116, "color": "#FFFFFF"},
        {"x": 120, "y": 118, "color": "#FFFFFF"},
        {"x": 122, "y": 116, "color": "#FFFFFF"}
      ]
    },
    {
      "duration": 90,
      "pixels": [
        {"x": 118, "y": 120, "color": "#D0D0FF"},
        {"x": 120, "y": 124, "color": "#FFFFFF"},
        {"x": 122, "y": 120, "color": "#D0D0FF"}
      ]
    },
    {
      "duration": 70,
      "pixels": [
        {"x": 118, "y": 116, "color": "#FFFFFF"},
        {"x": 120, "y": 118, "color": "#FFFFFF"},
        {"x": 122, "y": 116, "color": "#FFFFFF"}
      ]
    }
  ]
}